LICENSE
MANIFEST.in
README.md
requirements.txt
setup.cfg
setup.py
src/lengkapin/__init__.py
src/lengkapin.egg-info/PKG-INFO
src/lengkapin.egg-info/SOURCES.txt
src/lengkapin.egg-info/dependency_links.txt
src/lengkapin.egg-info/top_level.txt
src/lengkapin/common/__init__.py
src/lengkapin/common/base.py
src/lengkapin/django/__init__.py
src/lengkapin/django/admin.py
src/lengkapin/django/base.py
src/lengkapin/rest/__init__.py
src/lengkapin/rest/base.py