Metadata-Version: 2.1
Name: lengkapin
Version: 0.0.1
Summary: wip
Home-page: UNKNOWN
Author: Agung Yuliyanto
License: MIT
Platform: UNKNOWN
License-File: LICENSE
